bashhistory/__init__.py
bashhistory/bh_configs.py
bashhistory/bh_output.py
bashhistory/bh_parser.py
bashhistory/bh_utils.py
bashhistory/cli.py
bashhistory/db_commands.py
bashhistory/db_connection.py
bashhistory/query_creator.py
bashhistory/query_runner.py
bashhistorytests/__init__.py
bashhistorytests/test_bh_parser.py
bashhistory-1.2.0.dist-info/LICENSE
bashhistory-1.2.0.dist-info/METADATA
bashhistory-1.2.0.dist-info/WHEEL
bashhistory-1.2.0.dist-info/entry_points.txt
bashhistory-1.2.0.dist-info/top_level.txt
bashhistory-1.2.0.dist-info/RECORD
